MANIFEST.in
README
setup.py
django_qrcode.egg-info/PKG-INFO
django_qrcode.egg-info/SOURCES.txt
django_qrcode.egg-info/dependency_links.txt
django_qrcode.egg-info/not-zip-safe
django_qrcode.egg-info/top_level.txt
qrcode/__init__.py
qrcode/models.py
qrcode/tests.py
qrcode/utils.py
qrcode/views.py
qrcode/templates/qrcode/qr_tag.html
qrcode/templatetags/__init__.py
qrcode/templatetags/qr_tags.py