Metadata-Version: 1.0
Name: django-qrcode
Version: 0.3
Summary: Django application that provides simple templatetags to generate QR-codes
Home-page: https://github.com/zocolab/django-qrcode
Author: Pablo Recio Quijano
Author-email: pablo@zocolab.es
License: LGPL 3
Keywords: django qr code qrcode
Platform: UNKNOWN
Classifier: Development Status :: 4 - Beta
Classifier: Framework :: Django
Classifier: License :: OSI Approved :: GNU Library or Lesser General Public License (LGPL)
